cloudlab_client/__init__.py
cloudlab_client/client.py
cloudlab_client/test_client.py
cloudlab_client-0.1.140.dist-info/METADATA
cloudlab_client-0.1.140.dist-info/WHEEL
cloudlab_client-0.1.140.dist-info/RECORD
