Metadata-Version: 2.3
Name: cloudlab_client
Version: 0.1.140
Summary: Client for the cloudlab academic cloud environment.
Author: Yannis Zarkadas
Author-email: yanniszark@gmail.com
Requires-Python: >=3.8,<4.0
Classifier: Programming Language :: Python :: 3
Classifier: Programming Language :: Python :: 3.8
Classifier: Programming Language :: Python :: 3.9
Classifier: Programming Language :: Python :: 3.10
Classifier: Programming Language :: Python :: 3.11
Classifier: Programming Language :: Python :: 3.12
Classifier: Programming Language :: Python :: 3.13
Requires-Dist: requests (>=2.32.3,<3.0.0)
Requires-Dist: selenium (>=4.1.3,<5.0.0)
